justpeachy/__init__.py
justpeachy/core.py
tests/__init__.py
tests/test_core.py
JustPeachy-0.0.1.dist-info/METADATA
JustPeachy-0.0.1.dist-info/WHEEL
JustPeachy-0.0.1.dist-info/top_level.txt
JustPeachy-0.0.1.dist-info/RECORD
