Metadata-Version: 2.1
Name: JustPeachy
Version: 0.0.1
Summary: A basic 'hello world' package for a multi-agent autonomous AI agent system framework
Home-page: https://github.com/justpeachyai/JustPeachy
Author: JustPeachy.ai
Author-email: dev@justpeachy.ai
Classifier: Programming Language :: Python :: 3
Classifier: License :: OSI Approved :: MIT License
Classifier: Operating System :: OS Independent
Requires-Python: >=3.6
